{
  "key": "offer_extraction:3871180",
  "value": {
    "id": "3871180",
    "intitule": "Développeur .NET / Angular - Elasticsearch (H/F)",
    "entreprise": "",
    "territoire": "75 - Paris",
    "ville": "75056",
    "code_postal": "",
    "contrat": "CDI",
    "date_creation": "2026-06-17",
    "date": "2026-06-17",
    "url": "https://candidat.francetravail.fr/offres/recherche/detail/3871180",
    "description": "Nous recherchons un Développeur .NET / Angular autonome, capable d'intervenir sur des sujets variés autour du développement applicatif, de l'intégration web, des API, de la DataViz et d'Elasticsearch.Dans ce cadre, vos principales missions seront les suivantes :Développement applicatif en .NET ;Développement front-end avec Angular ;Développement et intégration d'API ;Intervention sur des sujets liés à Elasticsearch ;Participation à des travaux de DataViz ;Réalisation ou contribution à des prototypes Kibana ;Intégration web ;Contribution au suivi de sujets liés aux KPI et à la sécurité ;Encadrement et accompagnement d'un alternant déjà présent dans l'équipe.Environnement technique :.NET 10, Angular, Elasticsearch, Kibana, API, DataViz, intégration web, DevOps.",
    "metier": "Référenceur / Référenceuse web",
    "niveau": "junior",
    "competences": [],
    "salaire_min": 10000,
    "salaire_max": 10000,
    "teletravail": null,
    "diplomes_requis": [],
    "experience_requise": "Débutant accepté",
    "_extraction_metadata": {
      "extracted": true,
      "competences_count": 0,
      "diplomes_count": 0,
      "has_salary": false,
      "has_teletravail": false
    }
  },
  "computed_at": "2026-06-22T18:53:45.119134",
  "input_hash": "364a9b1a769454a90cf56155e97a5c3ac2f1224ee66ac2222ede50563a3d13e2",
  "source_version": "1.0",
  "model_version": "1.0",
  "status": "success"
}