{
  "key": "offer_extraction:8812987",
  "value": {
    "id": "8812987",
    "intitule": "Modern data Stack - Solution Architecte Snowflake (H/F)",
    "entreprise": "",
    "territoire": "92 - Levallois-Perret",
    "ville": "92044",
    "code_postal": "92300",
    "contrat": "Intérim - 1 Mois",
    "date_creation": "2026-02-06",
    "date": "2026-02-06",
    "url": "https://candidat.francetravail.fr/offres/recherche/detail/8812987",
    "description": "Vos Missions Clés :En tant que Solution Architect, vous êtes le garant de l'intégration et de la cohérence de toute la chaîne de valeur data :? 50% - Delivery et Implication ClientIntervenir en tant que Lead Architect sur nos projets clients stratégiques.Intervenir en tant qu'expert auprès de nouveaux comptes ou sur des sujets émergents.Délivrer des formations de pointe en tant qu'Authorized Trainer.Sécuriser nos projets en standardisant nos méthodes de delivery.? 25% - Business et Avant-venteApporter votre expertise lors des phases d'avant-vente : qualification, définition de la démarche technique, chiffrage et soutenance.Participer à l'identification et à la construction de nos offres clés (Migration, Setup Modern Platform, Snowflake Intelligence, etc.).Participer à l'effort de formation des équipes commerciales.? 25% - Expertise et R&amp;DMener une veille technologique active et identifier les sujets émergents.Piloter et contribuer aux projets de Recherche &amp; Développement.Contribuer au développement de nos assets et à la standardisation de nos méthodes de delivery.Participer à l'animation des communautés techniques internes.Participer activement au rayonnement externe de Devoteam Snowflake Partner (webinars, meetups, conférences, articles d'experts, etc.).",
    "metier": "Data engineer",
    "niveau": "junior",
    "competences": [
      "Intelligence artificielle",
      "Veille technologique",
      "Méthodologie Agile",
      "Sécurité informatique"
    ],
    "salaire_min": 50000,
    "salaire_max": 50000,
    "teletravail": null,
    "diplomes_requis": [],
    "experience_requise": "Débutant accepté",
    "_extraction_metadata": {
      "extracted": true,
      "competences_count": 4,
      "diplomes_count": 0,
      "has_salary": false,
      "has_teletravail": false
    }
  },
  "computed_at": "2026-06-22T18:51:39.865403",
  "input_hash": "8396775220b09fa72dbbb828c21ad9b1ee0f6d65352c57858cc4a29f02e4f18c",
  "source_version": "1.0",
  "model_version": "1.0",
  "status": "success"
}