{
  "key": "trends:92 - NEUILLY SUR SEINE",
  "value": {
    "territoire": "92 - NEUILLY SUR SEINE",
    "periode_jours": 365,
    "nombre_offres": 8,
    "competences": {
      "Intelligence artificielle": 6,
      "API": 5,
      "Backend": 5,
      "Gestion de projet": 5,
      "Qualité Des Données": 5,
      "SQL": 5,
      "Tests Automatisés": 5,
      "Architecture Microservices": 4,
      "Anglais Professionnel": 3,
      "Cybersécurité": 3,
      "Data engineering": 3,
      "Python": 3,
      "Sécurité Informatique": 3,
      "Analyse de données": 2,
      "API REST": 2,
      "Code Review": 2,
      "Documentation Technique": 2,
      "Ferroviaire": 2,
      "Model Drift": 2,
      "Résolution De Problèmes": 2,
      "Analyse Des Besoins": 1,
      "AWS": 1,
      "Azure": 1,
      "CSS": 1,
      "Design Patterns": 1,
      "Déploiement De Modèles": 1,
      "HTML": 1,
      "Intégration Continue": 1,
      "Java": 1,
      "MLOps": 1,
      "Optimisation Des Performances": 1,
      "TypeScript": 1,
      "Vision": 1,
      "Vue.js": 1
    },
    "competences_details": [
      {
        "nom": "Intelligence artificielle",
        "count": 6,
        "percentage": 75.0,
        "variants": {
          "Intelligence artificielle": 6
        }
      },
      {
        "nom": "API",
        "count": 5,
        "percentage": 62.5,
        "variants": {
          "API": 5
        }
      },
      {
        "nom": "Backend",
        "count": 5,
        "percentage": 62.5,
        "variants": {
          "Backend": 5
        }
      },
      {
        "nom": "Gestion de projet",
        "count": 5,
        "percentage": 62.5,
        "variants": {
          "Gestion de projet": 5
        }
      },
      {
        "nom": "Qualité Des Données",
        "count": 5,
        "percentage": 62.5,
        "variants": {
          "Qualité des données": 5
        }
      },
      {
        "nom": "SQL",
        "count": 5,
        "percentage": 62.5,
        "variants": {
          "SQL": 5
        }
      },
      {
        "nom": "Tests Automatisés",
        "count": 5,
        "percentage": 62.5,
        "variants": {
          "Tests automatisés": 5
        }
      },
      {
        "nom": "Architecture Microservices",
        "count": 4,
        "percentage": 50.0,
        "variants": {
          "Architecture microservices": 4
        }
      },
      {
        "nom": "Anglais Professionnel",
        "count": 3,
        "percentage": 37.5,
        "variants": {
          "Anglais professionnel": 2,
          "Anglais Professionnel": 1
        }
      },
      {
        "nom": "Cybersécurité",
        "count": 3,
        "percentage": 37.5,
        "variants": {
          "Cybersécurité": 3
        }
      },
      {
        "nom": "Data engineering",
        "count": 3,
        "percentage": 37.5,
        "variants": {
          "Data Engineering": 3
        }
      },
      {
        "nom": "Python",
        "count": 3,
        "percentage": 37.5,
        "variants": {
          "Python": 3
        }
      },
      {
        "nom": "Sécurité Informatique",
        "count": 3,
        "percentage": 37.5,
        "variants": {
          "Sécurité informatique": 3
        }
      },
      {
        "nom": "Analyse de données",
        "count": 2,
        "percentage": 25.0,
        "variants": {
          "Analyse de données": 2
        }
      },
      {
        "nom": "API REST",
        "count": 2,
        "percentage": 25.0,
        "variants": {
          "API REST": 1,
          "REST": 1
        }
      },
      {
        "nom": "Code Review",
        "count": 2,
        "percentage": 25.0,
        "variants": {
          "Code review": 2
        }
      },
      {
        "nom": "Documentation Technique",
        "count": 2,
        "percentage": 25.0,
        "variants": {
          "Documentation technique": 2
        }
      },
      {
        "nom": "Ferroviaire",
        "count": 2,
        "percentage": 25.0,
        "variants": {
          "Ferroviaire": 2
        }
      },
      {
        "nom": "Model Drift",
        "count": 2,
        "percentage": 25.0,
        "variants": {
          "Model drift": 2
        }
      },
      {
        "nom": "Résolution De Problèmes",
        "count": 2,
        "percentage": 25.0,
        "variants": {
          "Résolution de problèmes": 2
        }
      },
      {
        "nom": "Analyse Des Besoins",
        "count": 1,
        "percentage": 12.5,
        "variants": {
          "Analyse des besoins": 1
        }
      },
      {
        "nom": "AWS",
        "count": 1,
        "percentage": 12.5,
        "variants": {
          "AWS": 1
        }
      },
      {
        "nom": "Azure",
        "count": 1,
        "percentage": 12.5,
        "variants": {
          "Azure": 1
        }
      },
      {
        "nom": "CSS",
        "count": 1,
        "percentage": 12.5,
        "variants": {
          "CSS": 1
        }
      },
      {
        "nom": "Design Patterns",
        "count": 1,
        "percentage": 12.5,
        "variants": {
          "Design patterns": 1
        }
      },
      {
        "nom": "Déploiement De Modèles",
        "count": 1,
        "percentage": 12.5,
        "variants": {
          "Déploiement de modèles": 1
        }
      },
      {
        "nom": "HTML",
        "count": 1,
        "percentage": 12.5,
        "variants": {
          "HTML": 1
        }
      },
      {
        "nom": "Intégration Continue",
        "count": 1,
        "percentage": 12.5,
        "variants": {
          "Intégration continue": 1
        }
      },
      {
        "nom": "Java",
        "count": 1,
        "percentage": 12.5,
        "variants": {
          "Java": 1
        }
      },
      {
        "nom": "MLOps",
        "count": 1,
        "percentage": 12.5,
        "variants": {
          "MLOps": 1
        }
      },
      {
        "nom": "Optimisation Des Performances",
        "count": 1,
        "percentage": 12.5,
        "variants": {
          "Optimisation des performances": 1
        }
      },
      {
        "nom": "TypeScript",
        "count": 1,
        "percentage": 12.5,
        "variants": {
          "TypeScript": 1
        }
      },
      {
        "nom": "Vision",
        "count": 1,
        "percentage": 12.5,
        "variants": {
          "Vision": 1
        }
      },
      {
        "nom": "Vue.js",
        "count": 1,
        "percentage": 12.5,
        "variants": {
          "Vue.js": 1
        }
      }
    ],
    "competences_variants": {
      "Intelligence artificielle": {
        "Intelligence artificielle": 6
      },
      "API": {
        "API": 5
      },
      "Backend": {
        "Backend": 5
      },
      "Gestion de projet": {
        "Gestion de projet": 5
      },
      "Qualité Des Données": {
        "Qualité des données": 5
      },
      "SQL": {
        "SQL": 5
      },
      "Tests Automatisés": {
        "Tests automatisés": 5
      },
      "Architecture Microservices": {
        "Architecture microservices": 4
      },
      "Anglais Professionnel": {
        "Anglais professionnel": 2,
        "Anglais Professionnel": 1
      },
      "Cybersécurité": {
        "Cybersécurité": 3
      },
      "Data engineering": {
        "Data Engineering": 3
      },
      "Python": {
        "Python": 3
      },
      "Sécurité Informatique": {
        "Sécurité informatique": 3
      },
      "Analyse de données": {
        "Analyse de données": 2
      },
      "API REST": {
        "REST": 1,
        "API REST": 1
      },
      "Code Review": {
        "Code review": 2
      },
      "Documentation Technique": {
        "Documentation technique": 2
      },
      "Ferroviaire": {
        "Ferroviaire": 2
      },
      "Model Drift": {
        "Model drift": 2
      },
      "Résolution De Problèmes": {
        "Résolution de problèmes": 2
      },
      "Analyse Des Besoins": {
        "Analyse des besoins": 1
      },
      "AWS": {
        "AWS": 1
      },
      "Azure": {
        "Azure": 1
      },
      "CSS": {
        "CSS": 1
      },
      "Design Patterns": {
        "Design patterns": 1
      },
      "Déploiement De Modèles": {
        "Déploiement de modèles": 1
      },
      "HTML": {
        "HTML": 1
      },
      "Intégration Continue": {
        "Intégration continue": 1
      },
      "Java": {
        "Java": 1
      },
      "MLOps": {
        "MLOps": 1
      },
      "Optimisation Des Performances": {
        "Optimisation des performances": 1
      },
      "TypeScript": {
        "TypeScript": 1
      },
      "Vision": {
        "Vision": 1
      },
      "Vue.js": {
        "Vue.js": 1
      }
    },
    "metiers": {
      "Développeur / Développeuse logiciel ou d'application": 3,
      "Ingénieur / Ingénieure R&D en industrie": 2,
      "Data Analyst": 1,
      "Développeur / Développeuse web": 1,
      "Ingénieur / Ingénieure d'étude informatique": 1
    },
    "niveau": {
      "junior": 1,
      "intermediaire": 7
    },
    "contrats": {
      "CDI": 8
    },
    "cooccurrences": [
      {
        "competence_a": "API",
        "competence_b": "Backend",
        "count": 5,
        "percentage": 62.5
      },
      {
        "competence_a": "Gestion de projet",
        "competence_b": "Qualité Des Données",
        "count": 5,
        "percentage": 62.5
      },
      {
        "competence_a": "API",
        "competence_b": "Architecture Microservices",
        "count": 4,
        "percentage": 50.0
      },
      {
        "competence_a": "API",
        "competence_b": "Intelligence artificielle",
        "count": 4,
        "percentage": 50.0
      },
      {
        "competence_a": "Architecture Microservices",
        "competence_b": "Backend",
        "count": 4,
        "percentage": 50.0
      },
      {
        "competence_a": "Backend",
        "competence_b": "Intelligence artificielle",
        "count": 4,
        "percentage": 50.0
      },
      {
        "competence_a": "Gestion de projet",
        "competence_b": "Tests Automatisés",
        "count": 4,
        "percentage": 50.0
      },
      {
        "competence_a": "Intelligence artificielle",
        "competence_b": "Tests Automatisés",
        "count": 4,
        "percentage": 50.0
      },
      {
        "competence_a": "Qualité Des Données",
        "competence_b": "Tests Automatisés",
        "count": 4,
        "percentage": 50.0
      },
      {
        "competence_a": "Anglais Professionnel",
        "competence_b": "Gestion de projet",
        "count": 3,
        "percentage": 37.5
      },
      {
        "competence_a": "Anglais Professionnel",
        "competence_b": "Qualité Des Données",
        "count": 3,
        "percentage": 37.5
      },
      {
        "competence_a": "Anglais Professionnel",
        "competence_b": "Tests Automatisés",
        "count": 3,
        "percentage": 37.5
      },
      {
        "competence_a": "API",
        "competence_b": "Gestion de projet",
        "count": 3,
        "percentage": 37.5
      },
      {
        "competence_a": "API",
        "competence_b": "Qualité Des Données",
        "count": 3,
        "percentage": 37.5
      },
      {
        "competence_a": "API",
        "competence_b": "SQL",
        "count": 3,
        "percentage": 37.5
      },
      {
        "competence_a": "API",
        "competence_b": "Tests Automatisés",
        "count": 3,
        "percentage": 37.5
      },
      {
        "competence_a": "Architecture Microservices",
        "competence_b": "Gestion de projet",
        "count": 3,
        "percentage": 37.5
      },
      {
        "competence_a": "Architecture Microservices",
        "competence_b": "Intelligence artificielle",
        "count": 3,
        "percentage": 37.5
      },
      {
        "competence_a": "Architecture Microservices",
        "competence_b": "Qualité Des Données",
        "count": 3,
        "percentage": 37.5
      },
      {
        "competence_a": "Architecture Microservices",
        "competence_b": "Tests Automatisés",
        "count": 3,
        "percentage": 37.5
      },
      {
        "competence_a": "Backend",
        "competence_b": "Gestion de projet",
        "count": 3,
        "percentage": 37.5
      },
      {
        "competence_a": "Backend",
        "competence_b": "Qualité Des Données",
        "count": 3,
        "percentage": 37.5
      },
      {
        "competence_a": "Backend",
        "competence_b": "SQL",
        "count": 3,
        "percentage": 37.5
      },
      {
        "competence_a": "Backend",
        "competence_b": "Tests Automatisés",
        "count": 3,
        "percentage": 37.5
      },
      {
        "competence_a": "Cybersécurité",
        "competence_b": "Intelligence artificielle",
        "count": 3,
        "percentage": 37.5
      },
      {
        "competence_a": "Cybersécurité",
        "competence_b": "Tests Automatisés",
        "count": 3,
        "percentage": 37.5
      },
      {
        "competence_a": "Gestion de projet",
        "competence_b": "Intelligence artificielle",
        "count": 3,
        "percentage": 37.5
      },
      {
        "competence_a": "Gestion de projet",
        "competence_b": "SQL",
        "count": 3,
        "percentage": 37.5
      },
      {
        "competence_a": "Gestion de projet",
        "competence_b": "Sécurité Informatique",
        "count": 3,
        "percentage": 37.5
      },
      {
        "competence_a": "Intelligence artificielle",
        "competence_b": "Python",
        "count": 3,
        "percentage": 37.5
      },
      {
        "competence_a": "Intelligence artificielle",
        "competence_b": "Qualité Des Données",
        "count": 3,
        "percentage": 37.5
      },
      {
        "competence_a": "Intelligence artificielle",
        "competence_b": "SQL",
        "count": 3,
        "percentage": 37.5
      },
      {
        "competence_a": "Qualité Des Données",
        "competence_b": "SQL",
        "count": 3,
        "percentage": 37.5
      },
      {
        "competence_a": "Qualité Des Données",
        "competence_b": "Sécurité Informatique",
        "count": 3,
        "percentage": 37.5
      },
      {
        "competence_a": "Sécurité Informatique",
        "competence_b": "Tests Automatisés",
        "count": 3,
        "percentage": 37.5
      },
      {
        "competence_a": "Analyse de données",
        "competence_b": "Gestion de projet",
        "count": 2,
        "percentage": 25.0
      },
      {
        "competence_a": "Analyse de données",
        "competence_b": "Qualité Des Données",
        "count": 2,
        "percentage": 25.0
      },
      {
        "competence_a": "Analyse de données",
        "competence_b": "Sécurité Informatique",
        "count": 2,
        "percentage": 25.0
      },
      {
        "competence_a": "Analyse de données",
        "competence_b": "Tests Automatisés",
        "count": 2,
        "percentage": 25.0
      },
      {
        "competence_a": "Anglais Professionnel",
        "competence_b": "Architecture Microservices",
        "count": 2,
        "percentage": 25.0
      },
      {
        "competence_a": "Anglais Professionnel",
        "competence_b": "Backend",
        "count": 2,
        "percentage": 25.0
      },
      {
        "competence_a": "Anglais Professionnel",
        "competence_b": "Data engineering",
        "count": 2,
        "percentage": 25.0
      },
      {
        "competence_a": "Anglais Professionnel",
        "competence_b": "Documentation Technique",
        "count": 2,
        "percentage": 25.0
      },
      {
        "competence_a": "Anglais Professionnel",
        "competence_b": "Intelligence artificielle",
        "count": 2,
        "percentage": 25.0
      },
      {
        "competence_a": "Anglais Professionnel",
        "competence_b": "Résolution De Problèmes",
        "count": 2,
        "percentage": 25.0
      },
      {
        "competence_a": "Anglais Professionnel",
        "competence_b": "SQL",
        "count": 2,
        "percentage": 25.0
      },
      {
        "competence_a": "Anglais Professionnel",
        "competence_b": "Sécurité Informatique",
        "count": 2,
        "percentage": 25.0
      },
      {
        "competence_a": "API",
        "competence_b": "Anglais Professionnel",
        "count": 2,
        "percentage": 25.0
      },
      {
        "competence_a": "API",
        "competence_b": "API REST",
        "count": 2,
        "percentage": 25.0
      },
      {
        "competence_a": "API",
        "competence_b": "Code Review",
        "count": 2,
        "percentage": 25.0
      },
      {
        "competence_a": "API",
        "competence_b": "Cybersécurité",
        "count": 2,
        "percentage": 25.0
      },
      {
        "competence_a": "API",
        "competence_b": "Data engineering",
        "count": 2,
        "percentage": 25.0
      },
      {
        "competence_a": "API",
        "competence_b": "Documentation Technique",
        "count": 2,
        "percentage": 25.0
      },
      {
        "competence_a": "API",
        "competence_b": "Python",
        "count": 2,
        "percentage": 25.0
      },
      {
        "competence_a": "API REST",
        "competence_b": "Anglais Professionnel",
        "count": 2,
        "percentage": 25.0
      },
      {
        "competence_a": "API REST",
        "competence_b": "Architecture Microservices",
        "count": 2,
        "percentage": 25.0
      },
      {
        "competence_a": "API REST",
        "competence_b": "Backend",
        "count": 2,
        "percentage": 25.0
      },
      {
        "competence_a": "API REST",
        "competence_b": "Documentation Technique",
        "count": 2,
        "percentage": 25.0
      },
      {
        "competence_a": "API REST",
        "competence_b": "Gestion de projet",
        "count": 2,
        "percentage": 25.0
      },
      {
        "competence_a": "API REST",
        "competence_b": "Intelligence artificielle",
        "count": 2,
        "percentage": 25.0
      },
      {
        "competence_a": "API REST",
        "competence_b": "Qualité Des Données",
        "count": 2,
        "percentage": 25.0
      },
      {
        "competence_a": "API REST",
        "competence_b": "Tests Automatisés",
        "count": 2,
        "percentage": 25.0
      },
      {
        "competence_a": "Architecture Microservices",
        "competence_b": "Cybersécurité",
        "count": 2,
        "percentage": 25.0
      },
      {
        "competence_a": "Architecture Microservices",
        "competence_b": "Documentation Technique",
        "count": 2,
        "percentage": 25.0
      },
      {
        "competence_a": "Architecture Microservices",
        "competence_b": "SQL",
        "count": 2,
        "percentage": 25.0
      },
      {
        "competence_a": "Backend",
        "competence_b": "Code Review",
        "count": 2,
        "percentage": 25.0
      },
      {
        "competence_a": "Backend",
        "competence_b": "Cybersécurité",
        "count": 2,
        "percentage": 25.0
      },
      {
        "competence_a": "Backend",
        "competence_b": "Data engineering",
        "count": 2,
        "percentage": 25.0
      },
      {
        "competence_a": "Backend",
        "competence_b": "Documentation Technique",
        "count": 2,
        "percentage": 25.0
      },
      {
        "competence_a": "Backend",
        "competence_b": "Python",
        "count": 2,
        "percentage": 25.0
      },
      {
        "competence_a": "Code Review",
        "competence_b": "SQL",
        "count": 2,
        "percentage": 25.0
      },
      {
        "competence_a": "Cybersécurité",
        "competence_b": "Ferroviaire",
        "count": 2,
        "percentage": 25.0
      },
      {
        "competence_a": "Cybersécurité",
        "competence_b": "Gestion de projet",
        "count": 2,
        "percentage": 25.0
      },
      {
        "competence_a": "Cybersécurité",
        "competence_b": "Python",
        "count": 2,
        "percentage": 25.0
      },
      {
        "competence_a": "Cybersécurité",
        "competence_b": "Qualité Des Données",
        "count": 2,
        "percentage": 25.0
      },
      {
        "competence_a": "Data engineering",
        "competence_b": "Gestion de projet",
        "count": 2,
        "percentage": 25.0
      },
      {
        "competence_a": "Data engineering",
        "competence_b": "Intelligence artificielle",
        "count": 2,
        "percentage": 25.0
      },
      {
        "competence_a": "Data engineering",
        "competence_b": "Model Drift",
        "count": 2,
        "percentage": 25.0
      },
      {
        "competence_a": "Data engineering",
        "competence_b": "Qualité Des Données",
        "count": 2,
        "percentage": 25.0
      },
      {
        "competence_a": "Data engineering",
        "competence_b": "SQL",
        "count": 2,
        "percentage": 25.0
      },
      {
        "competence_a": "Data engineering",
        "competence_b": "Sécurité Informatique",
        "count": 2,
        "percentage": 25.0
      },
      {
        "competence_a": "Data engineering",
        "competence_b": "Tests Automatisés",
        "count": 2,
        "percentage": 25.0
      },
      {
        "competence_a": "Documentation Technique",
        "competence_b": "Gestion de projet",
        "count": 2,
        "percentage": 25.0
      },
      {
        "competence_a": "Documentation Technique",
        "competence_b": "Intelligence artificielle",
        "count": 2,
        "percentage": 25.0
      },
      {
        "competence_a": "Documentation Technique",
        "competence_b": "Qualité Des Données",
        "count": 2,
        "percentage": 25.0
      },
      {
        "competence_a": "Documentation Technique",
        "competence_b": "Tests Automatisés",
        "count": 2,
        "percentage": 25.0
      },
      {
        "competence_a": "Ferroviaire",
        "competence_b": "Intelligence artificielle",
        "count": 2,
        "percentage": 25.0
      },
      {
        "competence_a": "Ferroviaire",
        "competence_b": "Python",
        "count": 2,
        "percentage": 25.0
      },
      {
        "competence_a": "Ferroviaire",
        "competence_b": "Tests Automatisés",
        "count": 2,
        "percentage": 25.0
      },
      {
        "competence_a": "Gestion de projet",
        "competence_b": "Résolution De Problèmes",
        "count": 2,
        "percentage": 25.0
      },
      {
        "competence_a": "Intelligence artificielle",
        "competence_b": "Sécurité Informatique",
        "count": 2,
        "percentage": 25.0
      },
      {
        "competence_a": "Model Drift",
        "competence_b": "SQL",
        "count": 2,
        "percentage": 25.0
      },
      {
        "competence_a": "Python",
        "competence_b": "Tests Automatisés",
        "count": 2,
        "percentage": 25.0
      },
      {
        "competence_a": "Qualité Des Données",
        "competence_b": "Résolution De Problèmes",
        "count": 2,
        "percentage": 25.0
      },
      {
        "competence_a": "Résolution De Problèmes",
        "competence_b": "SQL",
        "count": 2,
        "percentage": 25.0
      },
      {
        "competence_a": "Résolution De Problèmes",
        "competence_b": "Tests Automatisés",
        "count": 2,
        "percentage": 25.0
      },
      {
        "competence_a": "SQL",
        "competence_b": "Tests Automatisés",
        "count": 2,
        "percentage": 25.0
      },
      {
        "competence_a": "Analyse de données",
        "competence_b": "Anglais Professionnel",
        "count": 1,
        "percentage": 12.5
      },
      {
        "competence_a": "Analyse de données",
        "competence_b": "Cybersécurité",
        "count": 1,
        "percentage": 12.5
      },
      {
        "competence_a": "Analyse de données",
        "competence_b": "Data engineering",
        "count": 1,
        "percentage": 12.5
      },
      {
        "competence_a": "Analyse de données",
        "competence_b": "Ferroviaire",
        "count": 1,
        "percentage": 12.5
      },
      {
        "competence_a": "Analyse de données",
        "competence_b": "Intelligence artificielle",
        "count": 1,
        "percentage": 12.5
      },
      {
        "competence_a": "Analyse de données",
        "competence_b": "Intégration Continue",
        "count": 1,
        "percentage": 12.5
      },
      {
        "competence_a": "Analyse de données",
        "competence_b": "Model Drift",
        "count": 1,
        "percentage": 12.5
      },
      {
        "competence_a": "Analyse de données",
        "competence_b": "Python",
        "count": 1,
        "percentage": 12.5
      },
      {
        "competence_a": "Analyse de données",
        "competence_b": "Résolution De Problèmes",
        "count": 1,
        "percentage": 12.5
      },
      {
        "competence_a": "Analyse de données",
        "competence_b": "SQL",
        "count": 1,
        "percentage": 12.5
      },
      {
        "competence_a": "Analyse de données",
        "competence_b": "Vision",
        "count": 1,
        "percentage": 12.5
      },
      {
        "competence_a": "Analyse Des Besoins",
        "competence_b": "Analyse de données",
        "count": 1,
        "percentage": 12.5
      },
      {
        "competence_a": "Analyse Des Besoins",
        "competence_b": "Anglais Professionnel",
        "count": 1,
        "percentage": 12.5
      },
      {
        "competence_a": "Analyse Des Besoins",
        "competence_b": "Data engineering",
        "count": 1,
        "percentage": 12.5
      },
      {
        "competence_a": "Analyse Des Besoins",
        "competence_b": "Gestion de projet",
        "count": 1,
        "percentage": 12.5
      },
      {
        "competence_a": "Analyse Des Besoins",
        "competence_b": "Model Drift",
        "count": 1,
        "percentage": 12.5
      },
      {
        "competence_a": "Analyse Des Besoins",
        "competence_b": "Qualité Des Données",
        "count": 1,
        "percentage": 12.5
      },
      {
        "competence_a": "Analyse Des Besoins",
        "competence_b": "Résolution De Problèmes",
        "count": 1,
        "percentage": 12.5
      },
      {
        "competence_a": "Analyse Des Besoins",
        "competence_b": "SQL",
        "count": 1,
        "percentage": 12.5
      },
      {
        "competence_a": "Analyse Des Besoins",
        "competence_b": "Sécurité Informatique",
        "count": 1,
        "percentage": 12.5
      },
      {
        "competence_a": "Analyse Des Besoins",
        "competence_b": "Tests Automatisés",
        "count": 1,
        "percentage": 12.5
      },
      {
        "competence_a": "Anglais Professionnel",
        "competence_b": "CSS",
        "count": 1,
        "percentage": 12.5
      },
      {
        "competence_a": "Anglais Professionnel",
        "competence_b": "Cybersécurité",
        "count": 1,
        "percentage": 12.5
      },
      {
        "competence_a": "Anglais Professionnel",
        "competence_b": "HTML",
        "count": 1,
        "percentage": 12.5
      },
      {
        "competence_a": "Anglais Professionnel",
        "competence_b": "Java",
        "count": 1,
        "percentage": 12.5
      },
      {
        "competence_a": "Anglais Professionnel",
        "competence_b": "Model Drift",
        "count": 1,
        "percentage": 12.5
      },
      {
        "competence_a": "Anglais Professionnel",
        "competence_b": "TypeScript",
        "count": 1,
        "percentage": 12.5
      },
      {
        "competence_a": "API",
        "competence_b": "AWS",
        "count": 1,
        "percentage": 12.5
      },
      {
        "competence_a": "API",
        "competence_b": "Azure",
        "count": 1,
        "percentage": 12.5
      },
      {
        "competence_a": "API",
        "competence_b": "CSS",
        "count": 1,
        "percentage": 12.5
      },
      {
        "competence_a": "API",
        "competence_b": "Design Patterns",
        "count": 1,
        "percentage": 12.5
      },
      {
        "competence_a": "API",
        "competence_b": "Déploiement De Modèles",
        "count": 1,
        "percentage": 12.5
      },
      {
        "competence_a": "API",
        "competence_b": "Ferroviaire",
        "count": 1,
        "percentage": 12.5
      },
      {
        "competence_a": "API",
        "competence_b": "HTML",
        "count": 1,
        "percentage": 12.5
      },
      {
        "competence_a": "API",
        "competence_b": "Java",
        "count": 1,
        "percentage": 12.5
      },
      {
        "competence_a": "API",
        "competence_b": "MLOps",
        "count": 1,
        "percentage": 12.5
      },
      {
        "competence_a": "API",
        "competence_b": "Model Drift",
        "count": 1,
        "percentage": 12.5
      },
      {
        "competence_a": "API",
        "competence_b": "Optimisation Des Performances",
        "count": 1,
        "percentage": 12.5
      },
      {
        "competence_a": "API",
        "competence_b": "Résolution De Problèmes",
        "count": 1,
        "percentage": 12.5
      },
      {
        "competence_a": "API",
        "competence_b": "Sécurité Informatique",
        "count": 1,
        "percentage": 12.5
      },
      {
        "competence_a": "API",
        "competence_b": "TypeScript",
        "count": 1,
        "percentage": 12.5
      },
      {
        "competence_a": "API",
        "competence_b": "Vue.js",
        "count": 1,
        "percentage": 12.5
      },
      {
        "competence_a": "API REST",
        "competence_b": "CSS",
        "count": 1,
        "percentage": 12.5
      },
      {
        "competence_a": "API REST",
        "competence_b": "Cybersécurité",
        "count": 1,
        "percentage": 12.5
      },
      {
        "competence_a": "API REST",
        "competence_b": "Data engineering",
        "count": 1,
        "percentage": 12.5
      },
      {
        "competence_a": "API REST",
        "competence_b": "HTML",
        "count": 1,
        "percentage": 12.5
      },
      {
        "competence_a": "API REST",
        "competence_b": "Java",
        "count": 1,
        "percentage": 12.5
      },
      {
        "competence_a": "API REST",
        "competence_b": "Résolution De Problèmes",
        "count": 1,
        "percentage": 12.5
      },
      {
        "competence_a": "API REST",
        "competence_b": "SQL",
        "count": 1,
        "percentage": 12.5
      },
      {
        "competence_a": "API REST",
        "competence_b": "Sécurité Informatique",
        "count": 1,
        "percentage": 12.5
      },
      {
        "competence_a": "API REST",
        "competence_b": "TypeScript",
        "count": 1,
        "percentage": 12.5
      },
      {
        "competence_a": "Architecture Microservices",
        "competence_b": "Code Review",
        "count": 1,
        "percentage": 12.5
      },
      {
        "competence_a": "Architecture Microservices",
        "competence_b": "CSS",
        "count": 1,
        "percentage": 12.5
      },
      {
        "competence_a": "Architecture Microservices",
        "competence_b": "Data engineering",
        "count": 1,
        "percentage": 12.5
      },
      {
        "competence_a": "Architecture Microservices",
        "competence_b": "Design Patterns",
        "count": 1,
        "percentage": 12.5
      },
      {
        "competence_a": "Architecture Microservices",
        "competence_b": "Ferroviaire",
        "count": 1,
        "percentage": 12.5
      },
      {
        "competence_a": "Architecture Microservices",
        "competence_b": "HTML",
        "count": 1,
        "percentage": 12.5
      },
      {
        "competence_a": "Architecture Microservices",
        "competence_b": "Java",
        "count": 1,
        "percentage": 12.5
      },
      {
        "competence_a": "Architecture Microservices",
        "competence_b": "Optimisation Des Performances",
        "count": 1,
        "percentage": 12.5
      },
      {
        "competence_a": "Architecture Microservices",
        "competence_b": "Python",
        "count": 1,
        "percentage": 12.5
      },
      {
        "competence_a": "Architecture Microservices",
        "competence_b": "Résolution De Problèmes",
        "count": 1,
        "percentage": 12.5
      },
      {
        "competence_a": "Architecture Microservices",
        "competence_b": "Sécurité Informatique",
        "count": 1,
        "percentage": 12.5
      },
      {
        "competence_a": "Architecture Microservices",
        "competence_b": "TypeScript",
        "count": 1,
        "percentage": 12.5
      },
      {
        "competence_a": "AWS",
        "competence_b": "Azure",
        "count": 1,
        "percentage": 12.5
      },
      {
        "competence_a": "AWS",
        "competence_b": "Backend",
        "count": 1,
        "percentage": 12.5
      },
      {
        "competence_a": "AWS",
        "competence_b": "Code Review",
        "count": 1,
        "percentage": 12.5
      },
      {
        "competence_a": "AWS",
        "competence_b": "Data engineering",
        "count": 1,
        "percentage": 12.5
      },
      {
        "competence_a": "AWS",
        "competence_b": "Déploiement De Modèles",
        "count": 1,
        "percentage": 12.5
      },
      {
        "competence_a": "AWS",
        "competence_b": "Intelligence artificielle",
        "count": 1,
        "percentage": 12.5
      },
      {
        "competence_a": "AWS",
        "competence_b": "MLOps",
        "count": 1,
        "percentage": 12.5
      },
      {
        "competence_a": "AWS",
        "competence_b": "Model Drift",
        "count": 1,
        "percentage": 12.5
      },
      {
        "competence_a": "AWS",
        "competence_b": "Python",
        "count": 1,
        "percentage": 12.5
      },
      {
        "competence_a": "AWS",
        "competence_b": "SQL",
        "count": 1,
        "percentage": 12.5
      },
      {
        "competence_a": "AWS",
        "competence_b": "Vue.js",
        "count": 1,
        "percentage": 12.5
      },
      {
        "competence_a": "Azure",
        "competence_b": "Backend",
        "count": 1,
        "percentage": 12.5
      },
      {
        "competence_a": "Azure",
        "competence_b": "Code Review",
        "count": 1,
        "percentage": 12.5
      },
      {
        "competence_a": "Azure",
        "competence_b": "Data engineering",
        "count": 1,
        "percentage": 12.5
      },
      {
        "competence_a": "Azure",
        "competence_b": "Déploiement De Modèles",
        "count": 1,
        "percentage": 12.5
      },
      {
        "competence_a": "Azure",
        "competence_b": "Intelligence artificielle",
        "count": 1,
        "percentage": 12.5
      },
      {
        "competence_a": "Azure",
        "competence_b": "MLOps",
        "count": 1,
        "percentage": 12.5
      },
      {
        "competence_a": "Azure",
        "competence_b": "Model Drift",
        "count": 1,
        "percentage": 12.5
      },
      {
        "competence_a": "Azure",
        "competence_b": "Python",
        "count": 1,
        "percentage": 12.5
      },
      {
        "competence_a": "Azure",
        "competence_b": "SQL",
        "count": 1,
        "percentage": 12.5
      },
      {
        "competence_a": "Azure",
        "competence_b": "Vue.js",
        "count": 1,
        "percentage": 12.5
      },
      {
        "competence_a": "Backend",
        "competence_b": "CSS",
        "count": 1,
        "percentage": 12.5
      },
      {
        "competence_a": "Backend",
        "competence_b": "Design Patterns",
        "count": 1,
        "percentage": 12.5
      },
      {
        "competence_a": "Backend",
        "competence_b": "Déploiement De Modèles",
        "count": 1,
        "percentage": 12.5
      },
      {
        "competence_a": "Backend",
        "competence_b": "Ferroviaire",
        "count": 1,
        "percentage": 12.5
      },
      {
        "competence_a": "Backend",
        "competence_b": "HTML",
        "count": 1,
        "percentage": 12.5
      },
      {
        "competence_a": "Backend",
        "competence_b": "Java",
        "count": 1,
        "percentage": 12.5
      },
      {
        "competence_a": "Backend",
        "competence_b": "MLOps",
        "count": 1,
        "percentage": 12.5
      },
      {
        "competence_a": "Backend",
        "competence_b": "Model Drift",
        "count": 1,
        "percentage": 12.5
      },
      {
        "competence_a": "Backend",
        "competence_b": "Optimisation Des Performances",
        "count": 1,
        "percentage": 12.5
      },
      {
        "competence_a": "Backend",
        "competence_b": "Résolution De Problèmes",
        "count": 1,
        "percentage": 12.5
      },
      {
        "competence_a": "Backend",
        "competence_b": "Sécurité Informatique",
        "count": 1,
        "percentage": 12.5
      },
      {
        "competence_a": "Backend",
        "competence_b": "TypeScript",
        "count": 1,
        "percentage": 12.5
      },
      {
        "competence_a": "Backend",
        "competence_b": "Vue.js",
        "count": 1,
        "percentage": 12.5
      },
      {
        "competence_a": "Code Review",
        "competence_b": "Data engineering",
        "count": 1,
        "percentage": 12.5
      },
      {
        "competence_a": "Code Review",
        "competence_b": "Design Patterns",
        "count": 1,
        "percentage": 12.5
      },
      {
        "competence_a": "Code Review",
        "competence_b": "Déploiement De Modèles",
        "count": 1,
        "percentage": 12.5
      },
      {
        "competence_a": "Code Review",
        "competence_b": "Gestion de projet",
        "count": 1,
        "percentage": 12.5
      },
      {
        "competence_a": "Code Review",
        "competence_b": "Intelligence artificielle",
        "count": 1,
        "percentage": 12.5
      },
      {
        "competence_a": "Code Review",
        "competence_b": "MLOps",
        "count": 1,
        "percentage": 12.5
      },
      {
        "competence_a": "Code Review",
        "competence_b": "Model Drift",
        "count": 1,
        "percentage": 12.5
      },
      {
        "competence_a": "Code Review",
        "competence_b": "Python",
        "count": 1,
        "percentage": 12.5
      },
      {
        "competence_a": "Code Review",
        "competence_b": "Qualité Des Données",
        "count": 1,
        "percentage": 12.5
      },
      {
        "competence_a": "Code Review",
        "competence_b": "Vue.js",
        "count": 1,
        "percentage": 12.5
      },
      {
        "competence_a": "CSS",
        "competence_b": "Data engineering",
        "count": 1,
        "percentage": 12.5
      },
      {
        "competence_a": "CSS",
        "competence_b": "Documentation Technique",
        "count": 1,
        "percentage": 12.5
      },
      {
        "competence_a": "CSS",
        "competence_b": "Gestion de projet",
        "count": 1,
        "percentage": 12.5
      },
      {
        "competence_a": "CSS",
        "competence_b": "HTML",
        "count": 1,
        "percentage": 12.5
      },
      {
        "competence_a": "CSS",
        "competence_b": "Intelligence artificielle",
        "count": 1,
        "percentage": 12.5
      },
      {
        "competence_a": "CSS",
        "competence_b": "Java",
        "count": 1,
        "percentage": 12.5
      },
      {
        "competence_a": "CSS",
        "competence_b": "Qualité Des Données",
        "count": 1,
        "percentage": 12.5
      },
      {
        "competence_a": "CSS",
        "competence_b": "Sécurité Informatique",
        "count": 1,
        "percentage": 12.5
      },
      {
        "competence_a": "CSS",
        "competence_b": "Tests Automatisés",
        "count": 1,
        "percentage": 12.5
      },
      {
        "competence_a": "CSS",
        "competence_b": "TypeScript",
        "count": 1,
        "percentage": 12.5
      },
      {
        "competence_a": "Cybersécurité",
        "competence_b": "Documentation Technique",
        "count": 1,
        "percentage": 12.5
      },
      {
        "competence_a": "Cybersécurité",
        "competence_b": "Intégration Continue",
        "count": 1,
        "percentage": 12.5
      },
      {
        "competence_a": "Cybersécurité",
        "competence_b": "Optimisation Des Performances",
        "count": 1,
        "percentage": 12.5
      },
      {
        "competence_a": "Cybersécurité",
        "competence_b": "Résolution De Problèmes",
        "count": 1,
        "percentage": 12.5
      },
      {
        "competence_a": "Cybersécurité",
        "competence_b": "SQL",
        "count": 1,
        "percentage": 12.5
      },
      {
        "competence_a": "Cybersécurité",
        "competence_b": "Sécurité Informatique",
        "count": 1,
        "percentage": 12.5
      },
      {
        "competence_a": "Cybersécurité",
        "competence_b": "Vision",
        "count": 1,
        "percentage": 12.5
      },
      {
        "competence_a": "Data engineering",
        "competence_b": "Documentation Technique",
        "count": 1,
        "percentage": 12.5
      },
      {
        "competence_a": "Data engineering",
        "competence_b": "Déploiement De Modèles",
        "count": 1,
        "percentage": 12.5
      },
      {
        "competence_a": "Data engineering",
        "competence_b": "HTML",
        "count": 1,
        "percentage": 12.5
      },
      {
        "competence_a": "Data engineering",
        "competence_b": "Java",
        "count": 1,
        "percentage": 12.5
      },
      {
        "competence_a": "Data engineering",
        "competence_b": "MLOps",
        "count": 1,
        "percentage": 12.5
      },
      {
        "competence_a": "Data engineering",
        "competence_b": "Python",
        "count": 1,
        "percentage": 12.5
      },
      {
        "competence_a": "Data engineering",
        "competence_b": "Résolution De Problèmes",
        "count": 1,
        "percentage": 12.5
      },
      {
        "competence_a": "Data engineering",
        "competence_b": "TypeScript",
        "count": 1,
        "percentage": 12.5
      },
      {
        "competence_a": "Data engineering",
        "competence_b": "Vue.js",
        "count": 1,
        "percentage": 12.5
      },
      {
        "competence_a": "Design Patterns",
        "competence_b": "Gestion de projet",
        "count": 1,
        "percentage": 12.5
      },
      {
        "competence_a": "Design Patterns",
        "competence_b": "Qualité Des Données",
        "count": 1,
        "percentage": 12.5
      },
      {
        "competence_a": "Design Patterns",
        "competence_b": "SQL",
        "count": 1,
        "percentage": 12.5
      },
      {
        "competence_a": "Documentation Technique",
        "competence_b": "HTML",
        "count": 1,
        "percentage": 12.5
      },
      {
        "competence_a": "Documentation Technique",
        "competence_b": "Java",
        "count": 1,
        "percentage": 12.5
      },
      {
        "competence_a": "Documentation Technique",
        "competence_b": "Résolution De Problèmes",
        "count": 1,
        "percentage": 12.5
      },
      {
        "competence_a": "Documentation Technique",
        "competence_b": "SQL",
        "count": 1,
        "percentage": 12.5
      },
      {
        "competence_a": "Documentation Technique",
        "competence_b": "Sécurité Informatique",
        "count": 1,
        "percentage": 12.5
      },
      {
        "competence_a": "Documentation Technique",
        "competence_b": "TypeScript",
        "count": 1,
        "percentage": 12.5
      },
      {
        "competence_a": "Déploiement De Modèles",
        "competence_b": "Intelligence artificielle",
        "count": 1,
        "percentage": 12.5
      },
      {
        "competence_a": "Déploiement De Modèles",
        "competence_b": "MLOps",
        "count": 1,
        "percentage": 12.5
      },
      {
        "competence_a": "Déploiement De Modèles",
        "competence_b": "Model Drift",
        "count": 1,
        "percentage": 12.5
      },
      {
        "competence_a": "Déploiement De Modèles",
        "competence_b": "Python",
        "count": 1,
        "percentage": 12.5
      },
      {
        "competence_a": "Déploiement De Modèles",
        "competence_b": "SQL",
        "count": 1,
        "percentage": 12.5
      },
      {
        "competence_a": "Déploiement De Modèles",
        "competence_b": "Vue.js",
        "count": 1,
        "percentage": 12.5
      },
      {
        "competence_a": "Ferroviaire",
        "competence_b": "Gestion de projet",
        "count": 1,
        "percentage": 12.5
      },
      {
        "competence_a": "Ferroviaire",
        "competence_b": "Intégration Continue",
        "count": 1,
        "percentage": 12.5
      },
      {
        "competence_a": "Ferroviaire",
        "competence_b": "Optimisation Des Performances",
        "count": 1,
        "percentage": 12.5
      },
      {
        "competence_a": "Ferroviaire",
        "competence_b": "Qualité Des Données",
        "count": 1,
        "percentage": 12.5
      },
      {
        "competence_a": "Ferroviaire",
        "competence_b": "Sécurité Informatique",
        "count": 1,
        "percentage": 12.5
      },
      {
        "competence_a": "Ferroviaire",
        "competence_b": "Vision",
        "count": 1,
        "percentage": 12.5
      },
      {
        "competence_a": "Gestion de projet",
        "competence_b": "HTML",
        "count": 1,
        "percentage": 12.5
      },
      {
        "competence_a": "Gestion de projet",
        "competence_b": "Intégration Continue",
        "count": 1,
        "percentage": 12.5
      },
      {
        "competence_a": "Gestion de projet",
        "competence_b": "Java",
        "count": 1,
        "percentage": 12.5
      },
      {
        "competence_a": "Gestion de projet",
        "competence_b": "Model Drift",
        "count": 1,
        "percentage": 12.5
      },
      {
        "competence_a": "Gestion de projet",
        "competence_b": "Python",
        "count": 1,
        "percentage": 12.5
      },
      {
        "competence_a": "Gestion de projet",
        "competence_b": "TypeScript",
        "count": 1,
        "percentage": 12.5
      },
      {
        "competence_a": "Gestion de projet",
        "competence_b": "Vision",
        "count": 1,
        "percentage": 12.5
      },
      {
        "competence_a": "HTML",
        "competence_b": "Intelligence artificielle",
        "count": 1,
        "percentage": 12.5
      },
      {
        "competence_a": "HTML",
        "competence_b": "Java",
        "count": 1,
        "percentage": 12.5
      },
      {
        "competence_a": "HTML",
        "competence_b": "Qualité Des Données",
        "count": 1,
        "percentage": 12.5
      },
      {
        "competence_a": "HTML",
        "competence_b": "Sécurité Informatique",
        "count": 1,
        "percentage": 12.5
      },
      {
        "competence_a": "HTML",
        "competence_b": "Tests Automatisés",
        "count": 1,
        "percentage": 12.5
      },
      {
        "competence_a": "HTML",
        "competence_b": "TypeScript",
        "count": 1,
        "percentage": 12.5
      },
      {
        "competence_a": "Intelligence artificielle",
        "competence_b": "Intégration Continue",
        "count": 1,
        "percentage": 12.5
      },
      {
        "competence_a": "Intelligence artificielle",
        "competence_b": "Java",
        "count": 1,
        "percentage": 12.5
      },
      {
        "competence_a": "Intelligence artificielle",
        "competence_b": "MLOps",
        "count": 1,
        "percentage": 12.5
      },
      {
        "competence_a": "Intelligence artificielle",
        "competence_b": "Model Drift",
        "count": 1,
        "percentage": 12.5
      },
      {
        "competence_a": "Intelligence artificielle",
        "competence_b": "Optimisation Des Performances",
        "count": 1,
        "percentage": 12.5
      },
      {
        "competence_a": "Intelligence artificielle",
        "competence_b": "Résolution De Problèmes",
        "count": 1,
        "percentage": 12.5
      },
      {
        "competence_a": "Intelligence artificielle",
        "competence_b": "TypeScript",
        "count": 1,
        "percentage": 12.5
      },
      {
        "competence_a": "Intelligence artificielle",
        "competence_b": "Vision",
        "count": 1,
        "percentage": 12.5
      },
      {
        "competence_a": "Intelligence artificielle",
        "competence_b": "Vue.js",
        "count": 1,
        "percentage": 12.5
      },
      {
        "competence_a": "Intégration Continue",
        "competence_b": "Python",
        "count": 1,
        "percentage": 12.5
      },
      {
        "competence_a": "Intégration Continue",
        "competence_b": "Qualité Des Données",
        "count": 1,
        "percentage": 12.5
      },
      {
        "competence_a": "Intégration Continue",
        "competence_b": "Sécurité Informatique",
        "count": 1,
        "percentage": 12.5
      },
      {
        "competence_a": "Intégration Continue",
        "competence_b": "Tests Automatisés",
        "count": 1,
        "percentage": 12.5
      },
      {
        "competence_a": "Intégration Continue",
        "competence_b": "Vision",
        "count": 1,
        "percentage": 12.5
      },
      {
        "competence_a": "Java",
        "competence_b": "Qualité Des Données",
        "count": 1,
        "percentage": 12.5
      },
      {
        "competence_a": "Java",
        "competence_b": "Sécurité Informatique",
        "count": 1,
        "percentage": 12.5
      },
      {
        "competence_a": "Java",
        "competence_b": "Tests Automatisés",
        "count": 1,
        "percentage": 12.5
      },
      {
        "competence_a": "Java",
        "competence_b": "TypeScript",
        "count": 1,
        "percentage": 12.5
      },
      {
        "competence_a": "MLOps",
        "competence_b": "Model Drift",
        "count": 1,
        "percentage": 12.5
      },
      {
        "competence_a": "MLOps",
        "competence_b": "Python",
        "count": 1,
        "percentage": 12.5
      },
      {
        "competence_a": "MLOps",
        "competence_b": "SQL",
        "count": 1,
        "percentage": 12.5
      },
      {
        "competence_a": "MLOps",
        "competence_b": "Vue.js",
        "count": 1,
        "percentage": 12.5
      },
      {
        "competence_a": "Model Drift",
        "competence_b": "Python",
        "count": 1,
        "percentage": 12.5
      },
      {
        "competence_a": "Model Drift",
        "competence_b": "Qualité Des Données",
        "count": 1,
        "percentage": 12.5
      },
      {
        "competence_a": "Model Drift",
        "competence_b": "Résolution De Problèmes",
        "count": 1,
        "percentage": 12.5
      },
      {
        "competence_a": "Model Drift",
        "competence_b": "Sécurité Informatique",
        "count": 1,
        "percentage": 12.5
      },
      {
        "competence_a": "Model Drift",
        "competence_b": "Tests Automatisés",
        "count": 1,
        "percentage": 12.5
      },
      {
        "competence_a": "Model Drift",
        "competence_b": "Vue.js",
        "count": 1,
        "percentage": 12.5
      },
      {
        "competence_a": "Optimisation Des Performances",
        "competence_b": "Python",
        "count": 1,
        "percentage": 12.5
      },
      {
        "competence_a": "Optimisation Des Performances",
        "competence_b": "Tests Automatisés",
        "count": 1,
        "percentage": 12.5
      },
      {
        "competence_a": "Python",
        "competence_b": "Qualité Des Données",
        "count": 1,
        "percentage": 12.5
      },
      {
        "competence_a": "Python",
        "competence_b": "SQL",
        "count": 1,
        "percentage": 12.5
      },
      {
        "competence_a": "Python",
        "competence_b": "Sécurité Informatique",
        "count": 1,
        "percentage": 12.5
      },
      {
        "competence_a": "Python",
        "competence_b": "Vision",
        "count": 1,
        "percentage": 12.5
      },
      {
        "competence_a": "Python",
        "competence_b": "Vue.js",
        "count": 1,
        "percentage": 12.5
      },
      {
        "competence_a": "Qualité Des Données",
        "competence_b": "TypeScript",
        "count": 1,
        "percentage": 12.5
      },
      {
        "competence_a": "Qualité Des Données",
        "competence_b": "Vision",
        "count": 1,
        "percentage": 12.5
      },
      {
        "competence_a": "Résolution De Problèmes",
        "competence_b": "Sécurité Informatique",
        "count": 1,
        "percentage": 12.5
      },
      {
        "competence_a": "SQL",
        "competence_b": "Sécurité Informatique",
        "count": 1,
        "percentage": 12.5
      },
      {
        "competence_a": "SQL",
        "competence_b": "Vue.js",
        "count": 1,
        "percentage": 12.5
      },
      {
        "competence_a": "Sécurité Informatique",
        "competence_b": "TypeScript",
        "count": 1,
        "percentage": 12.5
      },
      {
        "competence_a": "Sécurité Informatique",
        "competence_b": "Vision",
        "count": 1,
        "percentage": 12.5
      },
      {
        "competence_a": "Tests Automatisés",
        "competence_b": "TypeScript",
        "count": 1,
        "percentage": 12.5
      },
      {
        "competence_a": "Tests Automatisés",
        "competence_b": "Vision",
        "count": 1,
        "percentage": 12.5
      }
    ],
    "fiabilite": 0.2,
    "skill_sets": [
      [
        "Gestion de projet",
        "Intelligence artificielle",
        "SQL",
        "API REST",
        "Anglais Professionnel",
        "Tests Automatisés",
        "Qualité Des Données",
        "Cybersécurité",
        "API",
        "Architecture Microservices",
        "Backend",
        "Documentation Technique",
        "Résolution De Problèmes"
      ],
      [
        "Gestion de projet",
        "SQL",
        "Analyse de données",
        "Data engineering",
        "Anglais Professionnel",
        "Tests Automatisés",
        "Analyse Des Besoins",
        "Qualité Des Données",
        "Sécurité Informatique",
        "Model Drift",
        "Résolution De Problèmes"
      ],
      [
        "SQL",
        "Gestion de projet",
        "Code Review",
        "Qualité Des Données",
        "API",
        "Architecture Microservices",
        "Backend",
        "Design Patterns"
      ],
      [
        "Intelligence artificielle",
        "SQL"
      ],
      [
        "AWS",
        "Azure",
        "Intelligence artificielle",
        "Python",
        "SQL",
        "Vue.js",
        "MLOps",
        "Data engineering",
        "Déploiement De Modèles",
        "API",
        "Backend",
        "Model Drift",
        "Code Review"
      ],
      [
        "Intelligence artificielle",
        "Python",
        "Analyse de données",
        "Gestion de projet",
        "Ferroviaire",
        "Vision",
        "Cybersécurité",
        "Tests Automatisés",
        "Sécurité Informatique",
        "Qualité Des Données",
        "Intégration Continue"
      ],
      [
        "Intelligence artificielle",
        "Python",
        "Ferroviaire",
        "Tests Automatisés",
        "Optimisation Des Performances",
        "API",
        "Backend",
        "Cybersécurité",
        "Architecture Microservices"
      ],
      [
        "API REST",
        "CSS",
        "Gestion de projet",
        "HTML",
        "Intelligence artificielle",
        "Java",
        "TypeScript",
        "Data engineering",
        "Anglais Professionnel",
        "Tests Automatisés",
        "Documentation Technique",
        "Qualité Des Données",
        "API",
        "Architecture Microservices",
        "Backend",
        "Sécurité Informatique"
      ]
    ],
    "offres": [
      {
        "id": "209VCSD",
        "intitule": "Ingénieur Validation Systèmes (H/F)",
        "entreprise": "VULCAIN SERVICES",
        "territoire": "92 - NEUILLY SUR SEINE",
        "contrat": "CDI",
        "date": "2026-06-16",
        "url": "https://candidat.francetravail.fr/offres/recherche/detail/209VCSD"
      },
      {
        "id": "209TSNQ",
        "intitule": "Développeur C# (H/F)",
        "entreprise": "TESSELATE FRANCE",
        "territoire": "92 - NEUILLY SUR SEINE",
        "contrat": "CDI",
        "date": "2026-06-15",
        "url": "https://candidat.francetravail.fr/offres/recherche/detail/209TSNQ"
      },
      {
        "id": "209TSQC",
        "intitule": "Développeur Java (H/F)",
        "entreprise": "TESSELATE FRANCE",
        "territoire": "92 - NEUILLY SUR SEINE",
        "contrat": "CDI",
        "date": "2026-06-15",
        "url": "https://candidat.francetravail.fr/offres/recherche/detail/209TSQC"
      },
      {
        "id": "209NBBY",
        "intitule": "Ingénieur.e Systèmes Electriques (H/F)",
        "entreprise": "VULCAIN SERVICES",
        "territoire": "92 - NEUILLY SUR SEINE",
        "contrat": "CDI",
        "date": "2026-06-09",
        "url": "https://candidat.francetravail.fr/offres/recherche/detail/209NBBY"
      },
      {
        "id": "209CJMS",
        "intitule": "Développeur LoanIQ (H/F)",
        "entreprise": "TESSELATE FRANCE",
        "territoire": "92 - NEUILLY SUR SEINE",
        "contrat": "CDI",
        "date": "2026-06-02",
        "url": "https://candidat.francetravail.fr/offres/recherche/detail/209CJMS"
      },
      {
        "id": "207YDWX",
        "intitule": "Développeur BI - Strategy / Tableau Cloud sénior (H/F)",
        "entreprise": "PREREQUIS",
        "territoire": "92 - NEUILLY SUR SEINE",
        "contrat": "CDI",
        "date": "2026-05-06",
        "url": "https://candidat.francetravail.fr/offres/recherche/detail/207YDWX"
      },
      {
        "id": "207HNRS",
        "intitule": "Développeur Windev (H/F)",
        "entreprise": "SERIAL CODERS",
        "territoire": "92 - NEUILLY SUR SEINE",
        "contrat": "CDI",
        "date": "2026-04-22",
        "url": "https://candidat.francetravail.fr/offres/recherche/detail/207HNRS"
      },
      {
        "id": "207FFWH",
        "intitule": "Support Applicatif (H/F)",
        "entreprise": "TESSELATE FRANCE",
        "territoire": "92 - NEUILLY SUR SEINE",
        "contrat": "CDI",
        "date": "2026-04-20",
        "url": "https://candidat.francetravail.fr/offres/recherche/detail/207FFWH"
      }
    ],
    "offers": [
      {
        "id": "209VCSD",
        "intitule": "Ingénieur Validation Systèmes (H/F)",
        "entreprise": "VULCAIN SERVICES",
        "territoire": "92 - NEUILLY SUR SEINE",
        "contrat": "CDI",
        "date": "2026-06-16",
        "url": "https://candidat.francetravail.fr/offres/recherche/detail/209VCSD"
      },
      {
        "id": "209TSNQ",
        "intitule": "Développeur C# (H/F)",
        "entreprise": "TESSELATE FRANCE",
        "territoire": "92 - NEUILLY SUR SEINE",
        "contrat": "CDI",
        "date": "2026-06-15",
        "url": "https://candidat.francetravail.fr/offres/recherche/detail/209TSNQ"
      },
      {
        "id": "209TSQC",
        "intitule": "Développeur Java (H/F)",
        "entreprise": "TESSELATE FRANCE",
        "territoire": "92 - NEUILLY SUR SEINE",
        "contrat": "CDI",
        "date": "2026-06-15",
        "url": "https://candidat.francetravail.fr/offres/recherche/detail/209TSQC"
      },
      {
        "id": "209NBBY",
        "intitule": "Ingénieur.e Systèmes Electriques (H/F)",
        "entreprise": "VULCAIN SERVICES",
        "territoire": "92 - NEUILLY SUR SEINE",
        "contrat": "CDI",
        "date": "2026-06-09",
        "url": "https://candidat.francetravail.fr/offres/recherche/detail/209NBBY"
      },
      {
        "id": "209CJMS",
        "intitule": "Développeur LoanIQ (H/F)",
        "entreprise": "TESSELATE FRANCE",
        "territoire": "92 - NEUILLY SUR SEINE",
        "contrat": "CDI",
        "date": "2026-06-02",
        "url": "https://candidat.francetravail.fr/offres/recherche/detail/209CJMS"
      },
      {
        "id": "207YDWX",
        "intitule": "Développeur BI - Strategy / Tableau Cloud sénior (H/F)",
        "entreprise": "PREREQUIS",
        "territoire": "92 - NEUILLY SUR SEINE",
        "contrat": "CDI",
        "date": "2026-05-06",
        "url": "https://candidat.francetravail.fr/offres/recherche/detail/207YDWX"
      },
      {
        "id": "207HNRS",
        "intitule": "Développeur Windev (H/F)",
        "entreprise": "SERIAL CODERS",
        "territoire": "92 - NEUILLY SUR SEINE",
        "contrat": "CDI",
        "date": "2026-04-22",
        "url": "https://candidat.francetravail.fr/offres/recherche/detail/207HNRS"
      },
      {
        "id": "207FFWH",
        "intitule": "Support Applicatif (H/F)",
        "entreprise": "TESSELATE FRANCE",
        "territoire": "92 - NEUILLY SUR SEINE",
        "contrat": "CDI",
        "date": "2026-04-20",
        "url": "https://candidat.francetravail.fr/offres/recherche/detail/207FFWH"
      }
    ]
  },
  "computed_at": "2026-06-22T19:00:25.367346",
  "input_hash": "a457f685f1ebf34538f57311df6c7fe02bb909788fe743b1d28b53c544dd7c37",
  "source_version": "",
  "model_version": "",
  "status": "success"
}