{
  "key": "offer_extraction:209RJGQ",
  "value": {
    "id": "209RJGQ",
    "intitule": "Senior Pipeline Engineer - Subsea (H/F)",
    "entreprise": "COROTEC",
    "territoire": "78 - BOIS-D'ARCY",
    "ville": "78073",
    "code_postal": "78390",
    "contrat": "CDI",
    "date_creation": "2026-06-12",
    "date": "2026-06-12",
    "url": "https://candidat.francetravail.fr/offres/recherche/detail/209RJGQ",
    "description": "Dans le cadre du développement de nos activités dans le secteur de l'énergie et de l'offshore, nous recherchons un(e) Senior Pipeline Engineer pour intervenir sur des projets de conception et d'analyse de pipelines sous-marins.\n\nVous serez responsable des études techniques liées à l'intégrité, au dimensionnement et à l'analyse mécanique des pipelines rigides, en garantissant la conformité aux exigences clients et aux normes internationales applicables.\n\nVos missions\n- Réaliser des analyses par éléments finis (FEA) de pipelines sous-marins rigides. \n- Effectuer des études de lateral buckling (flambement latéral) et de pipeline walking. \n- Participer à la conception de spools et d'assemblages avec connecteurs mécaniques. \n- Réaliser les calculs de dimensionnement et les vérifications de conformité. \n- Appliquer les normes et recommandations techniques, notamment les standards DNV. \n- Développer et optimiser des outils d'automatisation et des workflows d'analyse sous Python. \n- Produire les notes de calcul, rapports techniques et documents d'ingénierie. \n- Assurer la coordination technique avec les différentes disciplines projet (structures, installation, matériaux, opérations, etc.). \n- Participer aux revues techniques avec les clients et les partenaires du projet. \n\n\nProfil recherché\n\nFormation\n- Diplôme d'Ingénieur ou Master en mécanique, génie civil, génie offshore, ou équivalent. \n\nExpérience\n- Minimum 8 à 10 ans d'expérience en ingénierie des pipelines offshore/subsea. \n- Expérience significative dans le secteur Oil & Gas. \n- Participation à des projets internationaux appréciée. \n\nCompétences techniques\n- Solide expérience en analyse par éléments finis (FEA). \n- Maîtrise d'Abaqus et de Python.\n- Connaissance approfondie des pipelines rigides sous-marins. \n- Maîtrise des problématiques de lateral buckling et pipeline walking. \n- Connaissance des normes DNV applicables aux pipelines offshore. \n- Bonne compréhension des méthodes d'installation et des contraintes opérationnelles offshore. \n- Anglais professionnel requis \n\nPourquoi nous rejoindre ?\nVous intégrerez des projets techniques de premier plan dans le domaine de l'énergie offshore et collaborerez avec des équipes d'experts au sein d'un environnement international stimulant.\n\nCe poste est ouvert aux consultants indépendants / freelances.",
    "metier": "Ingénieur / Ingénieure calcul et structure",
    "niveau": "intermediaire",
    "competences": [
      "Anglais Professionnel",
      "Intelligence artificielle",
      "Python",
      "Vue.js",
      "Automatisation de pipelines",
      "Data Engineering",
      "Tests automatisés",
      "API",
      "Backend",
      "Gestion de projet"
    ],
    "salaire_min": 50000,
    "salaire_max": 0,
    "teletravail": null,
    "diplomes_requis": [
      {
        "label": "Ingénieur",
        "level": 0,
        "required": true,
        "source_sentence": "Diplôme d'Ingénieur ou Master en mécanique, génie civil, génie offshore, ou équivalent.",
        "confidence": 0.9
      },
      {
        "label": "Master",
        "level": 8,
        "required": true,
        "source_sentence": "Diplôme d'Ingénieur ou Master en mécanique, génie civil, génie offshore, ou équivalent.",
        "confidence": 0.9
      }
    ],
    "experience_requise": "8 An(s)",
    "_extraction_metadata": {
      "extracted": true,
      "competences_count": 10,
      "diplomes_count": 2,
      "has_salary": false,
      "has_teletravail": false
    }
  },
  "computed_at": "2026-06-22T18:52:07.484863",
  "input_hash": "42757b05f8b2c67b3a49130c07a81288d613a325c43aff9b2fd221431fc815bf",
  "source_version": "1.0",
  "model_version": "1.0",
  "status": "success"
}