{
  "key": "offer_extraction:2573382",
  "value": {
    "id": "2573382",
    "intitule": "INGÉNIEUR ÉTUDES ET DÉVELOPPEMENT INFORMATIQUE (H/F)",
    "entreprise": "",
    "territoire": "67 - Strasbourg",
    "ville": "67482",
    "code_postal": "67000",
    "contrat": "Intérim - 18 Mois",
    "date_creation": "2026-05-13",
    "date": "2026-05-13",
    "url": "https://candidat.francetravail.fr/offres/recherche/detail/2573382",
    "description": "Nous recherchons pour le compte de notre client un Développeur Web Fullstack Python / FastAPI (F/H)Dans le cadre d'une croissance d'activité, notre client renforce son équipe technique dédiée au développement d'API FastAPI et d'outils web innovants en Vue.js. Sous la responsabilité du responsable technique, vous rejoignez une équipe de développeurs passionnés pour participer activement à la mise en place et à l'évolution de notre écosystème web.\n\nVos tâches principales :\n\nConception et Développement : Réaliser la conception technique et le développement (interfaces et services) en déclinant les choix d'architecture préconisés.\n\nFullstack : Développer les couches front-end et back-office (CRUD) conformément aux spécifications techniques détaillées.\n\nQualité logicielle : Programmer les fonctionnalités, documenter votre code et assurer les tests unitaires et d'intégration.\n\nMaintenance et Support : Assurer le support technique et la correction des problèmes remontés par les utilisateurs tout au long du cycle de vie de l'application.\n\nCollaboration : S'intégrer au sein du pôle et partager activement vos connaissances avec les autres membres de l'équipe pour tirer le collectif vers le haut.\n\nLe poste est proposé dans le cadre d'une longue tâche et le salaire est à négocier en fonction de votre expérience.",
    "metier": "Ingénieur / Ingénieure d'étude informatique",
    "niveau": "junior",
    "competences": [
      "FastAPI",
      "JavaScript",
      "Python",
      "Vue.js",
      "Tests automatisés",
      "Code review",
      "Documentation technique",
      "Gestion de projet",
      "Qualité des données"
    ],
    "salaire_min": null,
    "salaire_max": null,
    "teletravail": null,
    "diplomes_requis": [],
    "experience_requise": "Débutant accepté",
    "_extraction_metadata": {
      "extracted": true,
      "competences_count": 9,
      "diplomes_count": 0,
      "has_salary": false,
      "has_teletravail": false
    }
  },
  "computed_at": "2026-06-22T18:53:22.769362",
  "input_hash": "46d91eafc959513b4371ae47ec677955a1b0efe339ac042a392b8e059742e82e",
  "source_version": "1.0",
  "model_version": "1.0",
  "status": "success"
}