{
  "key": "offer_extraction:9318745",
  "value": {
    "id": "9318745",
    "intitule": "Data manager h/f",
    "entreprise": "",
    "territoire": "France",
    "ville": "France",
    "code_postal": "",
    "contrat": "CDI",
    "date_creation": "2026-02-20",
    "date": "2026-02-20",
    "url": "https://candidat.francetravail.fr/offres/recherche/detail/9318745",
    "description": "Votre mission : Faire de la donnée un levier direct de performance commerciale et de création de valeur métier pour l'ensemble du réseau.Structurer, fiabiliser et interconnecter le patrimoine informationnel afin de passer d'une donnée subie à une donnée déclencheuse de business.1. Architecte du patrimoine Data du réseauCartographier l'ensemble des flux et sources de données (GI / Facturation / Social / CRM / BI).Définir les standards de structuration, de qualité et de gouvernance.Sécuriser et uniformiser les référentiels.Construire le datalake interne du réseau.Déployer un socle BI robuste (Power BI) pour piloter la performance.\n2. Accélérateur de performance commerciale\nTransformer la donnée en produits data activables : triggers, scoring, segmentation intelligente.Alimenter les équipes commerciales en insights actionnables.Déployer des dashboards réseau orientés business et productivité.Mesurer et piloter la performance par cabinet, par offre, par segment.\n3. Chef d'orchestre des briques SI stratégiques\nPiloter la cohérence et l'interconnexion des outils structurants.Moderniser la brique GI / Facturation, socle de qualité des données internes.Interconnecter le SI Social (SILAE) avec la comptabilité et le CRM.Positionner HubSpot comme référentiel client unique.\n4. Bâtisseur d'équipe et leader transverse\nCréer et structurer la fonction Data au sein du réseau.Recruter et manager un Data Analyst / BI Expert.Définir les priorités, roadmaps et rituels de pilotage.Accompagner le changement auprès des équipes métiers et commerciales. \n5. Anticipation des croissances externes\nIntégrer l'impact des opérations de croissance externe en cours.Anticiper l'augmentation des volumes de flux et la complexification des systèmes.Définir une architecture scalable.Sécuriser les migrations et harmonisations post-acquisition.\nResponsabilités clés\nDéfinition de la roadmap Data &amp; BI du réseau.Construction du datalake et des flux d'interconnexion.Gouvernance et qualité des données.Déploiement des outils BI et indicateurs COMEX.Pilotage des projets transverses SI/Data.Management d'équipe.Reporting direct Direction Générale / COMEX.",
    "metier": "Data engineer",
    "niveau": "junior",
    "competences": [
      "Acquisition",
      "Intelligence artificielle",
      "Power BI",
      "Pilotage de la performance",
      "Scalabilité",
      "Qualité des données",
      "Data Engineering",
      "Pipelines de données",
      "Gestion de projet",
      "Sécurité informatique",
      "Analyse de données",
      "Feature Engineering",
      "Model drift"
    ],
    "salaire_min": null,
    "salaire_max": null,
    "teletravail": null,
    "diplomes_requis": [],
    "experience_requise": "Débutant accepté",
    "_extraction_metadata": {
      "extracted": true,
      "competences_count": 13,
      "diplomes_count": 0,
      "has_salary": false,
      "has_teletravail": false
    }
  },
  "computed_at": "2026-06-22T18:51:39.648207",
  "input_hash": "f6dc0a5c3fc1022ad36570cc57181ced7caaa95c7f2198dad64f2128c79c740e",
  "source_version": "1.0",
  "model_version": "1.0",
  "status": "success"
}